{
  "schema_version": "1.2",
  "project": {
    "title": "달리는 일기",
    "version": "1.0",
    "format": "diary",
    "created_at": "2026-02-25T00:00:00Z",
    "last_modified": "2026-02-25T00:00:00Z"
  },
  "progress": {
    "outline": "complete",
    "beat_plan": "complete",
    "draft": "in_progress",
    "total_word_count": 44584
  },
  "current": {
    "chapter": 1,
    "scene": 1
  },
  "diary": {
    "start_date": "2024-03-04",
    "end_date": "2025-03-02",
    "frequency": "twice_weekly",
    "current_date": "2024-07-29",
    "days": ["monday", "thursday"],
    "total_entries": 104
  },
  "protagonist": {
    "name": "김도윤",
    "age": 14,
    "grade": "중학교 1학년"
  },
  "open_threads": [],
  "resolved_threads": [],
  "scene_index": [
    {"scene_id": "entry_001", "date": "2024-03-04", "title": "중학교 첫날, 지옥 같은 버스", "status": "drafted", "word_count": 1087},
    {"scene_id": "entry_002", "date": "2024-03-07", "title": "버스, 매일 이래?", "status": "drafted", "word_count": 983},
    {"scene_id": "entry_003", "date": "2024-03-11", "title": "버스를 놓쳤다", "status": "drafted", "word_count": 1245},
    {"scene_id": "entry_004", "date": "2024-03-14", "title": "걸어서 간 날", "status": "drafted", "word_count": 1156},
    {"scene_id": "entry_005", "date": "2024-03-18", "title": "일부러 걸어봤다", "status": "drafted", "word_count": 1189},
    {"scene_id": "entry_006", "date": "2024-03-21", "title": "할아버지", "status": "drafted", "word_count": 1098},
    {"scene_id": "entry_007", "date": "2024-03-25", "title": "비 오는 날", "status": "drafted", "word_count": 987},
    {"scene_id": "entry_008", "date": "2024-03-28", "title": "엄마의 걱정", "status": "drafted", "word_count": 1142},
    {"scene_id": "entry_009", "date": "2024-04-01", "title": "4월, 봄이 왔다", "status": "drafted", "word_count": 1076},
    {"scene_id": "entry_010", "date": "2024-04-04", "title": "아침의 소리들", "status": "drafted", "word_count": 1034},
    {"scene_id": "entry_011", "date": "2024-04-08", "title": "주 2회 루틴", "status": "drafted", "word_count": 1067},
    {"scene_id": "entry_012", "date": "2024-04-11", "title": "할아버지의 감귤", "status": "drafted", "word_count": 1089},
    {"scene_id": "entry_013", "date": "2024-04-15", "title": "걷기가 당연해졌다", "status": "drafted", "word_count": 1023},
    {"scene_id": "entry_014", "date": "2024-04-18", "title": "시간이 아깝지 않아", "status": "drafted", "word_count": 1056},
    {"scene_id": "entry_015", "date": "2024-04-22", "title": "체육 시간", "status": "drafted", "word_count": 1108},
    {"scene_id": "entry_016", "date": "2024-04-25", "title": "봄비", "status": "drafted", "word_count": 1045},
    {"scene_id": "entry_017", "date": "2024-04-29", "title": "엄마가 이해하기 시작했다", "status": "drafted", "word_count": 1012},
    {"scene_id": "entry_018", "date": "2024-05-02", "title": "5월의 아침", "status": "drafted", "word_count": 987},
    {"scene_id": "entry_019", "date": "2024-05-06", "title": "뛰어봤다", "status": "drafted", "word_count": 1134},
    {"scene_id": "entry_020", "date": "2024-05-09", "title": "달리기가 이렇게 좋은 거였어?", "status": "drafted", "word_count": 1078},
    {"scene_id": "entry_021", "date": "2024-05-13", "title": "민서의 말", "status": "drafted", "word_count": 1034},
    {"scene_id": "entry_022", "date": "2024-05-16", "title": "달려서 등교", "status": "drafted", "word_count": 1089},
    {"scene_id": "entry_023", "date": "2024-05-20", "title": "실패", "status": "drafted", "word_count": 1023},
    {"scene_id": "entry_024", "date": "2024-05-23", "title": "운동화가 불편해", "status": "drafted", "word_count": 1056},
    {"scene_id": "entry_025", "date": "2024-05-27", "title": "할아버지의 응원", "status": "drafted", "word_count": 1067},
    {"scene_id": "entry_026", "date": "2024-06-03", "title": "러닝화의 마법", "status": "drafted", "word_count": 1045},
    {"scene_id": "entry_027", "date": "2024-06-06", "title": "장마가 시작됐다", "status": "drafted", "word_count": 1012},
    {"scene_id": "entry_028", "date": "2024-06-10", "title": "빗속을 달리다", "status": "drafted", "word_count": 1098},
    {"scene_id": "entry_029", "date": "2024-06-13", "title": "5km 논스톱", "status": "drafted", "word_count": 1056},
    {"scene_id": "entry_030", "date": "2024-06-17", "title": "선생님의 관심", "status": "drafted", "word_count": 1034},
    {"scene_id": "entry_031", "date": "2024-06-20", "title": "여름이 오고 있다", "status": "drafted", "word_count": 1023},
    {"scene_id": "entry_032", "date": "2024-06-24", "title": "땀", "status": "drafted", "word_count": 1012},
    {"scene_id": "entry_033", "date": "2024-06-27", "title": "민서 같이 달릴래?", "status": "drafted", "word_count": 1078},
    {"scene_id": "entry_034", "date": "2024-07-01", "title": "7월의 폭염", "status": "drafted", "word_count": 1034},
    {"scene_id": "entry_035", "date": "2024-07-04", "title": "더위와의 싸움", "status": "drafted", "word_count": 1067},
    {"scene_id": "entry_036", "date": "2024-07-08", "title": "태풍이 온다", "status": "drafted", "word_count": 1023},
    {"scene_id": "entry_037", "date": "2024-07-11", "title": "못 달린 지 3일", "status": "drafted", "word_count": 1012},
    {"scene_id": "entry_038", "date": "2024-07-15", "title": "태풍이 지나고", "status": "drafted", "word_count": 1045},
    {"scene_id": "entry_039", "date": "2024-07-18", "title": "왜 달리는 거지?", "status": "drafted", "word_count": 1056},
    {"scene_id": "entry_040", "date": "2024-07-22", "title": "다시 버스를 탔다", "status": "drafted", "word_count": 1034},
    {"scene_id": "entry_041", "date": "2024-07-25", "title": "슬럼프 탈출", "status": "drafted", "word_count": 1023},
    {"scene_id": "entry_042", "date": "2024-07-29", "title": "여름방학이 시작됐다", "status": "drafted", "word_count": 1067},
    {"scene_id": "entry_043", "date": "2024-08-01", "title": "10km를 향해", "status": "planned", "word_count": 0}
  ]
}
